pyplates/find_dupes.py
pyplates-0.1.0.dist-info/LICENSE
pyplates-0.1.0.dist-info/WHEEL
pyplates-0.1.0.dist-info/METADATA
pyplates-0.1.0.dist-info/RECORD
