Metadata-Version: 2.1
Name: pyplates
Version: 0.1.0
Summary: Project Template for python on macOS Big Sur
Home-page: https://skeptycal.github.io/as_loguru
License: MIT
Keywords: macOS,setup,terminal,ci,log,logging,cli,logger,pyproject,toml
Author: skeptycal
Author-email: skeptycal@gmail.com
Maintainer: skeptycal
Maintainer-email: skeptycal@gmail.com 
Requires-Python: >=3.6.1,<4.0.0
Classifier: Development Status :: 5 - Production/Stable
Classifier: Intended Audience :: Developers
Classifier: License :: OSI Approved :: MIT License
Classifier: Programming Language :: Python
Classifier: Programming Language :: Python :: 3
Classifier: Programming Language :: Python :: 3.6
Classifier: Programming Language :: Python :: 3.7
Classifier: Programming Language :: Python :: 3.8
Classifier: Programming Language :: Python :: Implementation :: CPython
Classifier: Programming Language :: Python :: Implementation :: PyPy
Classifier: Topic :: System :: Logging
Requires-Dist: aiocontextvars (>=0.2.0); python_version < "3.7"
Requires-Dist: colorama (>=0.4.3,<0.5.0); sys_platform == "win32"
Requires-Dist: loguru (>=0.5.1,<0.6.0)
Requires-Dist: pathlib2; python_version ~= "2.7" and sys_platform == "win32"
Requires-Dist: win32-setctime (>=1.0.0); sys_platform == "win32"
Project-URL: Documentation, https://skeptycal.github.io/as_loguru
Project-URL: Repository, https://github.com/skeptycal/as_loguru
